hugr/__init__.py
hugr/client.py
hugr/stream.py
hugr_client-0.1.1.dist-info/METADATA
hugr_client-0.1.1.dist-info/WHEEL
hugr_client-0.1.1.dist-info/top_level.txt
hugr_client-0.1.1.dist-info/RECORD
