Metadata-Version: 2.4
Name: hugr-client
Version: 0.1.1
Summary: Python client for Hugr Arrow IPC over multipart/mixed
Author-email: Hugr-lab <gribanov.vladimir@gmail.com>
Project-URL: Homepage, https://github.com/hugr-lab/hugr-client
Requires-Python: >=3.8
Requires-Dist: requests
Requires-Dist: pyarrow
Requires-Dist: pandas
Requires-Dist: geopandas
Requires-Dist: shapely
Requires-Dist: requests_toolbelt
Requires-Dist: numpy
Requires-Dist: shapely
Requires-Dist: keplergl
Requires-Dist: pydeck
Requires-Dist: folium
Requires-Dist: matplotlib
Requires-Dist: mapclassify
Requires-Dist: websockets
Requires-Dist: asyncio
